odoo8_addon_module_uninstall_check-8.0.1.0.0-py2.7-nspkg.pth
odoo8_addon_module_uninstall_check-8.0.1.0.0.dist-info/DESCRIPTION.rst
odoo8_addon_module_uninstall_check-8.0.1.0.0.dist-info/METADATA
odoo8_addon_module_uninstall_check-8.0.1.0.0.dist-info/RECORD
odoo8_addon_module_uninstall_check-8.0.1.0.0.dist-info/WHEEL
odoo8_addon_module_uninstall_check-8.0.1.0.0.dist-info/metadata.json
odoo8_addon_module_uninstall_check-8.0.1.0.0.dist-info/namespace_packages.txt
odoo8_addon_module_uninstall_check-8.0.1.0.0.dist-info/top_level.txt
odoo_addons/module_uninstall_check/README.rst
odoo_addons/module_uninstall_check/__init__.py
odoo_addons/module_uninstall_check/__openerp__.py
odoo_addons/module_uninstall_check/demo/res_groups.xml
odoo_addons/module_uninstall_check/i18n/fr.po
odoo_addons/module_uninstall_check/static/description/module_form.png
odoo_addons/module_uninstall_check/static/description/sale_margin_uninstallation.png
odoo_addons/module_uninstall_check/static/description/sale_uninstallation.png
odoo_addons/module_uninstall_check/views/ir_module_module.xml
odoo_addons/module_uninstall_check/wizards/__init__.py
odoo_addons/module_uninstall_check/wizards/action.xml
odoo_addons/module_uninstall_check/wizards/wizard_module_uninstall.py
odoo_addons/module_uninstall_check/wizards/wizard_module_uninstall.xml
odoo_addons/module_uninstall_check/wizards/wizard_module_uninstall_line.py
