Metadata-Version: 2.0
Name: odoo8-addon-module-uninstall-check
Version: 8.0.1.0.0
Summary: Add Extra Checks before uninstallation of modules
Home-page: https://odoo-community.org/
Author: GRAP, Odoo Community Association (OCA)
Author-email: support@odoo-community.org
License: AGPL-3
Platform: UNKNOWN
Classifier: Programming Language :: Python :: 2.7
Classifier: Framework :: Odoo
Classifier: License :: OSI Approved :: GNU Affero General Public License v3
Requires-Dist: odoo (<9.0a,>=8.0a)
